capture/__init__.py
capture/capture.py
trello_capture-1.0.1.dist-info/LICENSE
trello_capture-1.0.1.dist-info/METADATA
trello_capture-1.0.1.dist-info/WHEEL
trello_capture-1.0.1.dist-info/entry_points.txt
trello_capture-1.0.1.dist-info/top_level.txt
trello_capture-1.0.1.dist-info/RECORD
