Metadata-Version: 2.1
Name: trello-capture
Version: 1.0.1
Summary: Add cards to your Inbox from command line
Home-page: https://github.com/egegunes/trello-capture
Author: Ege Güneş
Author-email: egegunes@gmail.com
License: GPLv3
Platform: UNKNOWN
Requires-Dist: requests
